arlas_persistence_api_python/__init__.py
arlas_persistence_api_python/api_client.py
arlas_persistence_api_python/configuration.py
arlas_persistence_api_python/rest.py
arlas_persistence_api_python/apis/__init__.py
arlas_persistence_api_python/apis/persist_api.py
arlas_persistence_api_python/models/__init__.py
arlas_persistence_api_python/models/data_resource.py
arlas_persistence_api_python/models/data_with_links.py
arlas_persistence_api_python/models/error.py
arlas_persistence_api_python/models/exists.py
arlas_persistence_api_python/models/link.py
test/__init__.py
test/test_data_resource.py
test/test_data_with_links.py
test/test_error.py
test/test_exists.py
test/test_link.py
test/test_persist_api.py
arlas_persistence_api-24.1.0.dist-info/METADATA
arlas_persistence_api-24.1.0.dist-info/WHEEL
arlas_persistence_api-24.1.0.dist-info/top_level.txt
arlas_persistence_api-24.1.0.dist-info/RECORD
