Metadata-Version: 2.1
Name: arlas-persistence-api
Version: 24.1.0
Summary: ARLAS persistence API
Home-page: https://github.com/gisaia/ARLAS-persistence
Author: Gisaïa
Author-email: contact@gisaia.com
License: UNKNOWN
Keywords: Arlas,ARLAS persistence API
Platform: UNKNOWN
Requires-Dist: urllib3 (>=1.15)
Requires-Dist: six (>=1.10)
Requires-Dist: certifi
Requires-Dist: python-dateutil
